{"1920": {"count": 3599, "density": 0}, "1921": {"count": 3628, "density": 0}, "1922": {"count": 3657, "density": 0}, "1923": {"count": 3686, "density": 0}, "1924": {"count": 3715, "density": 0}, "1925": {"count": 3745, "density": 0}, "1926": {"count": 3775, "density": 0}, "1927": {"count": 3805, "density": 0}, "1928": {"count": 3835, "density": 0}, "1929": {"count": 3866, "density": 0}, "1930": {"count": 3897, "density": 0}, "1931": {"count": 3928, "density": 0}, "1932": {"count": 3959, "density": 0}, "1933": {"count": 3991, "density": 0}, "1934": {"count": 4023, "density": 0}, "1935": {"count": 4055, "density": 0}, "1936": {"count": 4087, "density": 0}, "1937": {"count": 4120, "density": 0}, "1938": {"count": 4153, "density": 0}, "1939": {"count": 4186, "density": 0}, "1940": {"count": 4219, "density": 0}, "1941": {"count": 4253, "density": 0}, "1942": {"count": 4287, "density": 0}, "1943": {"count": 4321, "density": 0}, "1944": {"count": 4355, "density": 0}, "1945": {"count": 4390, "density": 0}, "1946": {"count": 4425, "density": 0}, "1947": {"count": 4460, "density": 0}, "1948": {"count": 4495, "density": 0}, "1949": {"count": 4531, "density": 0}, "1950": {"count": 4567, "density": 19.857}, "1951": {"count": 4609, "density": 20.039}, "1952": {"count": 4648, "density": 20.209}, "1953": {"count": 4678, "density": 20.339}, "1954": {"count": 4721, "density": 20.526}, "1955": {"count": 4749, "density": 20.648}, "1956": {"count": 4801, "density": 20.874}, "1957": {"count": 4841, "density": 21.048}, "1958": {"count": 4886, "density": 21.243}, "1959": {"count": 4929, "density": 21.43}, "1960": {"count": 4975, "density": 21.63}, "1961": {"count": 5014, "density": 21.8}, "1962": {"count": 5041, "density": 21.917}, "1963": {"count": 5081, "density": 22.091}, "1964": {"count": 5120, "density": 22.261}, "1965": {"count": 5162, "density": 22.443}, "1966": {"count": 5229, "density": 22.735}, "1967": {"count": 5297, "density": 23.03}, "1968": {"count": 5380, "density": 23.391}, "1969": {"count": 5464, "density": 23.757}, "1970": {"count": 5551, "density": 24.135}, "1971": {"count": 5642, "density": 24.53}, "1972": {"count": 5753, "density": 25.013}, "1973": {"count": 5845, "density": 25.413}, "1974": {"count": 5932, "density": 25.791}, "1975": {"count": 6005, "density": 26.109}, "1976": {"count": 6051, "density": 26.309}, "1977": {"count": 6103, "density": 26.535}, "1978": {"count": 6122, "density": 26.617}, "1979": {"count": 6138, "density": 26.687}, "1980": {"count": 6129, "density": 26.648}, "1981": {"count": 6109, "density": 26.561}, "1982": {"count": 6067, "density": 26.378}, "1983": {"count": 6030, "density": 26.217}, "1984": {"count": 6003, "density": 26.1}, "1985": {"count": 6017, "density": 26.161}, "1986": {"count": 6068, "density": 26.383}, "1987": {"count": 6148, "density": 26.73}, "1988": {"count": 6236, "density": 27.113}, "1989": {"count": 6327, "density": 27.509}, "1990": {"count": 6385, "density": 27.761}, "1991": {"count": 6425, "density": 27.935}, "1992": {"count": 6435, "density": 27.978}, "1993": {"count": 6423, "density": 27.926}, "1994": {"count": 6416, "density": 27.896}, "1995": {"count": 6389, "density": 27.778}, "1996": {"count": 6375, "density": 27.717}, "1997": {"count": 6366, "density": 27.678}, "1998": {"count": 6350, "density": 27.609}, "1999": {"count": 6324, "density": 27.496}, "2000": {"count": 6298, "density": 27.383}, "2001": {"count": 6255, "density": 27.196}, "2002": {"count": 6207, "density": 26.987}, "2003": {"count": 6150, "density": 26.739}, "2004": {"count": 6118, "density": 26.6}, "2005": {"count": 6113, "density": 26.578}, "2006": {"count": 6160, "density": 26.783}, "2007": {"count": 6220, "density": 27.043}, "2008": {"count": 6286, "density": 27.33}, "2009": {"count": 6343, "density": 27.578}, "2010": {"count": 6361, "density": 27.657}, "2011": {"count": 6323, "density": 27.491}, "2012": {"count": 6251, "density": 27.178}, "2013": {"count": 6168, "density": 26.817}, "2014": {"count": 6073, "density": 26.404}, "2015": {"count": 5992, "density": 26.052}, "2016": {"count": 5933, "density": 25.796}, "2017": {"count": 5885, "density": 25.587}, "2018": {"count": 5845, "density": 25.413}, "2019": {"count": 5821, "density": 25.309}, "2020": {"count": 5795, "density": 25.196}, "development": [3599, 3628, 3657, 3686, 3715, 3745, 3775, 3805, 3835, 3866, 3897, 3928, 3959, 3991, 4023, 4055, 4087, 4120, 4153, 4186, 4219, 4253, 4287, 4321, 4355, 4390, 4425, 4460, 4495, 4531, 4567, 4609, 4648, 4678, 4721, 4749, 4801, 4841, 4886, 4929, 4975, 5014, 5041, 5081, 5120, 5162, 5229, 5297, 5380, 5464, 5551, 5642, 5753, 5845, 5932, 6005, 6051, 6103, 6122, 6138, 6129, 6109, 6067, 6030, 6003, 6017, 6068, 6148, 6236, 6327, 6385, 6425, 6435, 6423, 6416, 6389, 6375, 6366, 6350, 6324, 6298, 6255, 6207, 6150, 6118, 6113, 6160, 6220, 6286, 6343, 6361, 6323, 6251, 6168, 6073, 5992, 5933, 5885, 5845, 5821, 5795]}